{
  "domain": "data/planbench_public/mystery_bw/domain.pddl",
  "problem": "data/planbench_public/mystery_bw/problems/mystery_0028.pddl",
  "plan": "data/planbench_public/mystery_bw/plans_corrupt/mystery_0028_corrupt.txt",
  "initial_state": [
    "free t1",
    "free t2",
    "free t3",
    "free t4",
    "free t5",
    "free t6",
    "free t7",
    "grounded t1",
    "grounded t2",
    "grounded t3",
    "grounded t4",
    "grounded t5",
    "grounded t6",
    "grounded t7",
    "idle"
  ],
  "status": "invalid",
  "exit_code": 1,
  "validator_output": "Checking plan: data/planbench_public/mystery_bw/plans_corrupt/mystery_0028_corrupt.txt\nPlan to validate:\n\nPlan size: 13\n1:\n(lift t6)\n \n2:\n(bind t6 t7)\n \n3:\n(lift t5)\n \n4:\n(bind t5 t6)\n \n5:\n(lift t4)\n \n6:\n(bind t4 t5)\n \n7:\n(lift t3)\n \n8:\n(bind t3 t4)\n \n9:\n(lift t2)\n \n10:\n(bind t1 t2)\n \n11:\n(bind t2 t3)\n \n12:\n(lift t1)\n \n13:\n(bind t1 t2)\n \n\nPlan Validation details\n-----------------------\n\nChecking next happening (time 1)\nDeleting (grounded t6)\nDeleting (free t6)\nDeleting (idle)\nAdding (holding t6)\n\nChecking next happening (time 2)\nDeleting (holding t6)\nDeleting (free t7)\nAdding (rel t6 t7)\nAdding (free t6)\nAdding (idle)\n\nChecking next happening (time 3)\nDeleting (grounded t5)\nDeleting (free t5)\nDeleting (idle)\nAdding (holding t5)\n\nChecking next happening (time 4)\nDeleting (holding t5)\nDeleting (free t6)\nAdding (rel t5 t6)\nAdding (free t5)\nAdding (idle)\n\nChecking next happening (time 5)\nDeleting (grounded t4)\nDeleting (free t4)\nDeleting (idle)\nAdding (holding t4)\n\nChecking next happening (time 6)\nDeleting (holding t4)\nDeleting (free t5)\nAdding (rel t4 t5)\nAdding (free t4)\nAdding (idle)\n\nChecking next happening (time 7)\nDeleting (grounded t3)\nDeleting (free t3)\nDeleting (idle)\nAdding (holding t3)\n\nChecking next happening (time 8)\nDeleting (holding t3)\nDeleting (free t4)\nAdding (rel t3 t4)\nAdding (free t3)\nAdding (idle)\n\nChecking next happening (time 9)\nDeleting (grounded t2)\nDeleting (free t2)\nDeleting (idle)\nAdding (holding t2)\n\nChecking next happening (time 10)\nPlan failed because of unsatisfied precondition in:\n(bind t1 t2)\n\nPlan failed to execute\n\nPlan Repair Advice:\n\n(bind t1 t2) has an unsatisfied precondition at time 10\n(Follow each of:\n    (Set (holding t1) to true)\n    and (Set (free t2) to true)\n)\n\n\nFailed plans:\n data/planbench_public/mystery_bw/plans_corrupt/mystery_0028_corrupt.txt \n",
  "transitions": [
    {
      "step": 0,
      "time": 1.0,
      "action": "(lift t6)",
      "state": [
        "free t1",
        "free t2",
        "free t3",
        "free t4",
        "free t5",
        "free t6",
        "free t7",
        "grounded t1",
        "grounded t2",
        "grounded t3",
        "grounded t4",
        "grounded t5",
        "grounded t6",
        "grounded t7",
        "idle"
      ],
      "effects": {
        "del": [
          "grounded t6",
          "free t6",
          "idle"
        ],
        "add": [
          "holding t6"
        ]
      },
      "status": "valid",
      "next_state": [
        "free t1",
        "free t2",
        "free t3",
        "free t4",
        "free t5",
        "free t7",
        "grounded t1",
        "grounded t2",
        "grounded t3",
        "grounded t4",
        "grounded t5",
        "grounded t7",
        "holding t6"
      ],
      "errors": []
    },
    {
      "step": 1,
      "time": 2.0,
      "action": "(bind t6 t7)",
      "state": [
        "free t1",
        "free t2",
        "free t3",
        "free t4",
        "free t5",
        "free t7",
        "grounded t1",
        "grounded t2",
        "grounded t3",
        "grounded t4",
        "grounded t5",
        "grounded t7",
        "holding t6"
      ],
      "effects": {
        "del": [
          "holding t6",
          "free t7"
        ],
        "add": [
          "rel t6 t7",
          "free t6",
          "idle"
        ]
      },
      "status": "valid",
      "next_state": [
        "free t1",
        "free t2",
        "free t3",
        "free t4",
        "free t5",
        "free t6",
        "grounded t1",
        "grounded t2",
        "grounded t3",
        "grounded t4",
        "grounded t5",
        "grounded t7",
        "idle",
        "rel t6 t7"
      ],
      "errors": []
    },
    {
      "step": 2,
      "time": 3.0,
      "action": "(lift t5)",
      "state": [
        "free t1",
        "free t2",
        "free t3",
        "free t4",
        "free t5",
        "free t6",
        "grounded t1",
        "grounded t2",
        "grounded t3",
        "grounded t4",
        "grounded t5",
        "grounded t7",
        "idle",
        "rel t6 t7"
      ],
      "effects": {
        "del": [
          "grounded t5",
          "free t5",
          "idle"
        ],
        "add": [
          "holding t5"
        ]
      },
      "status": "valid",
      "next_state": [
        "free t1",
        "free t2",
        "free t3",
        "free t4",
        "free t6",
        "grounded t1",
        "grounded t2",
        "grounded t3",
        "grounded t4",
        "grounded t7",
        "holding t5",
        "rel t6 t7"
      ],
      "errors": []
    },
    {
      "step": 3,
      "time": 4.0,
      "action": "(bind t5 t6)",
      "state": [
        "free t1",
        "free t2",
        "free t3",
        "free t4",
        "free t6",
        "grounded t1",
        "grounded t2",
        "grounded t3",
        "grounded t4",
        "grounded t7",
        "holding t5",
        "rel t6 t7"
      ],
      "effects": {
        "del": [
          "holding t5",
          "free t6"
        ],
        "add": [
          "rel t5 t6",
          "free t5",
          "idle"
        ]
      },
      "status": "valid",
      "next_state": [
        "free t1",
        "free t2",
        "free t3",
        "free t4",
        "free t5",
        "grounded t1",
        "grounded t2",
        "grounded t3",
        "grounded t4",
        "grounded t7",
        "idle",
        "rel t5 t6",
        "rel t6 t7"
      ],
      "errors": []
    },
    {
      "step": 4,
      "time": 5.0,
      "action": "(lift t4)",
      "state": [
        "free t1",
        "free t2",
        "free t3",
        "free t4",
        "free t5",
        "grounded t1",
        "grounded t2",
        "grounded t3",
        "grounded t4",
        "grounded t7",
        "idle",
        "rel t5 t6",
        "rel t6 t7"
      ],
      "effects": {
        "del": [
          "grounded t4",
          "free t4",
          "idle"
        ],
        "add": [
          "holding t4"
        ]
      },
      "status": "valid",
      "next_state": [
        "free t1",
        "free t2",
        "free t3",
        "free t5",
        "grounded t1",
        "grounded t2",
        "grounded t3",
        "grounded t7",
        "holding t4",
        "rel t5 t6",
        "rel t6 t7"
      ],
      "errors": []
    },
    {
      "step": 5,
      "time": 6.0,
      "action": "(bind t4 t5)",
      "state": [
        "free t1",
        "free t2",
        "free t3",
        "free t5",
        "grounded t1",
        "grounded t2",
        "grounded t3",
        "grounded t7",
        "holding t4",
        "rel t5 t6",
        "rel t6 t7"
      ],
      "effects": {
        "del": [
          "holding t4",
          "free t5"
        ],
        "add": [
          "rel t4 t5",
          "free t4",
          "idle"
        ]
      },
      "status": "valid",
      "next_state": [
        "free t1",
        "free t2",
        "free t3",
        "free t4",
        "grounded t1",
        "grounded t2",
        "grounded t3",
        "grounded t7",
        "idle",
        "rel t4 t5",
        "rel t5 t6",
        "rel t6 t7"
      ],
      "errors": []
    },
    {
      "step": 6,
      "time": 7.0,
      "action": "(lift t3)",
      "state": [
        "free t1",
        "free t2",
        "free t3",
        "free t4",
        "grounded t1",
        "grounded t2",
        "grounded t3",
        "grounded t7",
        "idle",
        "rel t4 t5",
        "rel t5 t6",
        "rel t6 t7"
      ],
      "effects": {
        "del": [
          "grounded t3",
          "free t3",
          "idle"
        ],
        "add": [
          "holding t3"
        ]
      },
      "status": "valid",
      "next_state": [
        "free t1",
        "free t2",
        "free t4",
        "grounded t1",
        "grounded t2",
        "grounded t7",
        "holding t3",
        "rel t4 t5",
        "rel t5 t6",
        "rel t6 t7"
      ],
      "errors": []
    },
    {
      "step": 7,
      "time": 8.0,
      "action": "(bind t3 t4)",
      "state": [
        "free t1",
        "free t2",
        "free t4",
        "grounded t1",
        "grounded t2",
        "grounded t7",
        "holding t3",
        "rel t4 t5",
        "rel t5 t6",
        "rel t6 t7"
      ],
      "effects": {
        "del": [
          "holding t3",
          "free t4"
        ],
        "add": [
          "rel t3 t4",
          "free t3",
          "idle"
        ]
      },
      "status": "valid",
      "next_state": [
        "free t1",
        "free t2",
        "free t3",
        "grounded t1",
        "grounded t2",
        "grounded t7",
        "idle",
        "rel t3 t4",
        "rel t4 t5",
        "rel t5 t6",
        "rel t6 t7"
      ],
      "errors": []
    },
    {
      "step": 8,
      "time": 9.0,
      "action": "(lift t2)",
      "state": [
        "free t1",
        "free t2",
        "free t3",
        "grounded t1",
        "grounded t2",
        "grounded t7",
        "idle",
        "rel t3 t4",
        "rel t4 t5",
        "rel t5 t6",
        "rel t6 t7"
      ],
      "effects": {
        "del": [
          "grounded t2",
          "free t2",
          "idle"
        ],
        "add": [
          "holding t2"
        ]
      },
      "status": "valid",
      "next_state": [
        "free t1",
        "free t3",
        "grounded t1",
        "grounded t7",
        "holding t2",
        "rel t3 t4",
        "rel t4 t5",
        "rel t5 t6",
        "rel t6 t7"
      ],
      "errors": []
    },
    {
      "step": 9,
      "time": 10.0,
      "action": "(bind t1 t2)",
      "state": [
        "free t1",
        "free t3",
        "grounded t1",
        "grounded t7",
        "holding t2",
        "rel t3 t4",
        "rel t4 t5",
        "rel t5 t6",
        "rel t6 t7"
      ],
      "effects": {
        "del": [],
        "add": []
      },
      "status": "invalid",
      "next_state": [
        "free t1",
        "free t3",
        "grounded t1",
        "grounded t7",
        "holding t2",
        "rel t3 t4",
        "rel t4 t5",
        "rel t5 t6",
        "rel t6 t7"
      ],
      "errors": [
        "unsatisfied precondition in:",
        "(bind t1 t2)"
      ]
    }
  ],
  "errors": [
    "unsatisfied precondition in:",
    "(bind t1 t2)"
  ],
  "failed_at_step": 9,
  "plan_type": "corrupt"
}