{
  "domain": "data/planbench_public/mystery_bw/domain.pddl",
  "problem": "data/planbench_public/mystery_bw/problems/mystery_0095.pddl",
  "plan": "data/planbench_public/mystery_bw/plans_corrupt/mystery_0095_corrupt.txt",
  "initial_state": [
    "free t1",
    "free t2",
    "free t3",
    "free t4",
    "grounded t1",
    "grounded t2",
    "grounded t3",
    "grounded t4",
    "idle"
  ],
  "status": "invalid",
  "exit_code": 1,
  "validator_output": "Checking plan: data/planbench_public/mystery_bw/plans_corrupt/mystery_0095_corrupt.txt\nPlan to validate:\n\nPlan size: 7\n1:\n(lift t3)\n \n2:\n(bind t3 t4)\n \n3:\n(lift t2)\n \n4:\n(bind t1 t2)\n \n5:\n(bind t2 t3)\n \n6:\n(lift t1)\n \n7:\n(bind t1 t2)\n \n\nPlan Validation details\n-----------------------\n\nChecking next happening (time 1)\nDeleting (grounded t3)\nDeleting (free t3)\nDeleting (idle)\nAdding (holding t3)\n\nChecking next happening (time 2)\nDeleting (holding t3)\nDeleting (free t4)\nAdding (rel t3 t4)\nAdding (free t3)\nAdding (idle)\n\nChecking next happening (time 3)\nDeleting (grounded t2)\nDeleting (free t2)\nDeleting (idle)\nAdding (holding t2)\n\nChecking next happening (time 4)\nPlan failed because of unsatisfied precondition in:\n(bind t1 t2)\n\nPlan failed to execute\n\nPlan Repair Advice:\n\n(bind t1 t2) has an unsatisfied precondition at time 4\n(Follow each of:\n    (Set (holding t1) to true)\n    and (Set (free t2) to true)\n)\n\n\nFailed plans:\n data/planbench_public/mystery_bw/plans_corrupt/mystery_0095_corrupt.txt \n",
  "transitions": [
    {
      "step": 0,
      "time": 1.0,
      "action": "(lift t3)",
      "state": [
        "free t1",
        "free t2",
        "free t3",
        "free t4",
        "grounded t1",
        "grounded t2",
        "grounded t3",
        "grounded t4",
        "idle"
      ],
      "effects": {
        "del": [
          "grounded t3",
          "free t3",
          "idle"
        ],
        "add": [
          "holding t3"
        ]
      },
      "status": "valid",
      "next_state": [
        "free t1",
        "free t2",
        "free t4",
        "grounded t1",
        "grounded t2",
        "grounded t4",
        "holding t3"
      ],
      "errors": []
    },
    {
      "step": 1,
      "time": 2.0,
      "action": "(bind t3 t4)",
      "state": [
        "free t1",
        "free t2",
        "free t4",
        "grounded t1",
        "grounded t2",
        "grounded t4",
        "holding t3"
      ],
      "effects": {
        "del": [
          "holding t3",
          "free t4"
        ],
        "add": [
          "rel t3 t4",
          "free t3",
          "idle"
        ]
      },
      "status": "valid",
      "next_state": [
        "free t1",
        "free t2",
        "free t3",
        "grounded t1",
        "grounded t2",
        "grounded t4",
        "idle",
        "rel t3 t4"
      ],
      "errors": []
    },
    {
      "step": 2,
      "time": 3.0,
      "action": "(lift t2)",
      "state": [
        "free t1",
        "free t2",
        "free t3",
        "grounded t1",
        "grounded t2",
        "grounded t4",
        "idle",
        "rel t3 t4"
      ],
      "effects": {
        "del": [
          "grounded t2",
          "free t2",
          "idle"
        ],
        "add": [
          "holding t2"
        ]
      },
      "status": "valid",
      "next_state": [
        "free t1",
        "free t3",
        "grounded t1",
        "grounded t4",
        "holding t2",
        "rel t3 t4"
      ],
      "errors": []
    },
    {
      "step": 3,
      "time": 4.0,
      "action": "(bind t1 t2)",
      "state": [
        "free t1",
        "free t3",
        "grounded t1",
        "grounded t4",
        "holding t2",
        "rel t3 t4"
      ],
      "effects": {
        "del": [],
        "add": []
      },
      "status": "invalid",
      "next_state": [
        "free t1",
        "free t3",
        "grounded t1",
        "grounded t4",
        "holding t2",
        "rel t3 t4"
      ],
      "errors": [
        "unsatisfied precondition in:",
        "(bind t1 t2)"
      ]
    }
  ],
  "errors": [
    "unsatisfied precondition in:",
    "(bind t1 t2)"
  ],
  "failed_at_step": 3,
  "plan_type": "corrupt"
}