{
  "domain": "data/planbench_public/mystery_bw/domain.pddl",
  "problem": "data/planbench_public/mystery_bw/problems/mystery_0061.pddl",
  "plan": "data/planbench_public/mystery_bw/plans_valid/mystery_0061.txt",
  "initial_state": [
    "free t1",
    "free t2",
    "free t3",
    "free t4",
    "free t5",
    "grounded t1",
    "grounded t2",
    "grounded t3",
    "grounded t4",
    "grounded t5",
    "idle"
  ],
  "status": "valid",
  "exit_code": 0,
  "validator_output": "Checking plan: data/planbench_public/mystery_bw/plans_valid/mystery_0061.txt\nPlan to validate:\n\nPlan size: 8\n1:\n(lift t4)\n \n2:\n(bind t4 t5)\n \n3:\n(lift t3)\n \n4:\n(bind t3 t4)\n \n5:\n(lift t2)\n \n6:\n(bind t2 t3)\n \n7:\n(lift t1)\n \n8:\n(bind t1 t2)\n \n\nPlan Validation details\n-----------------------\n\nChecking next happening (time 1)\nDeleting (grounded t4)\nDeleting (free t4)\nDeleting (idle)\nAdding (holding t4)\n\nChecking next happening (time 2)\nDeleting (holding t4)\nDeleting (free t5)\nAdding (rel t4 t5)\nAdding (free t4)\nAdding (idle)\n\nChecking next happening (time 3)\nDeleting (grounded t3)\nDeleting (free t3)\nDeleting (idle)\nAdding (holding t3)\n\nChecking next happening (time 4)\nDeleting (holding t3)\nDeleting (free t4)\nAdding (rel t3 t4)\nAdding (free t3)\nAdding (idle)\n\nChecking next happening (time 5)\nDeleting (grounded t2)\nDeleting (free t2)\nDeleting (idle)\nAdding (holding t2)\n\nChecking next happening (time 6)\nDeleting (holding t2)\nDeleting (free t3)\nAdding (rel t2 t3)\nAdding (free t2)\nAdding (idle)\n\nChecking next happening (time 7)\nDeleting (grounded t1)\nDeleting (free t1)\nDeleting (idle)\nAdding (holding t1)\n\nChecking next happening (time 8)\nDeleting (holding t1)\nDeleting (free t2)\nAdding (rel t1 t2)\nAdding (free t1)\nAdding (idle)\nPlan executed successfully - checking goal\nPlan valid\nFinal value: 8 \n\nSuccessful plans:\nValue: 8\n data/planbench_public/mystery_bw/plans_valid/mystery_0061.txt 8 \n\n",
  "transitions": [
    {
      "step": 0,
      "time": 1.0,
      "action": "(lift t4)",
      "state": [
        "free t1",
        "free t2",
        "free t3",
        "free t4",
        "free t5",
        "grounded t1",
        "grounded t2",
        "grounded t3",
        "grounded t4",
        "grounded t5",
        "idle"
      ],
      "effects": {
        "del": [
          "grounded t4",
          "free t4",
          "idle"
        ],
        "add": [
          "holding t4"
        ]
      },
      "status": "valid",
      "next_state": [
        "free t1",
        "free t2",
        "free t3",
        "free t5",
        "grounded t1",
        "grounded t2",
        "grounded t3",
        "grounded t5",
        "holding t4"
      ],
      "errors": []
    },
    {
      "step": 1,
      "time": 2.0,
      "action": "(bind t4 t5)",
      "state": [
        "free t1",
        "free t2",
        "free t3",
        "free t5",
        "grounded t1",
        "grounded t2",
        "grounded t3",
        "grounded t5",
        "holding t4"
      ],
      "effects": {
        "del": [
          "holding t4",
          "free t5"
        ],
        "add": [
          "rel t4 t5",
          "free t4",
          "idle"
        ]
      },
      "status": "valid",
      "next_state": [
        "free t1",
        "free t2",
        "free t3",
        "free t4",
        "grounded t1",
        "grounded t2",
        "grounded t3",
        "grounded t5",
        "idle",
        "rel t4 t5"
      ],
      "errors": []
    },
    {
      "step": 2,
      "time": 3.0,
      "action": "(lift t3)",
      "state": [
        "free t1",
        "free t2",
        "free t3",
        "free t4",
        "grounded t1",
        "grounded t2",
        "grounded t3",
        "grounded t5",
        "idle",
        "rel t4 t5"
      ],
      "effects": {
        "del": [
          "grounded t3",
          "free t3",
          "idle"
        ],
        "add": [
          "holding t3"
        ]
      },
      "status": "valid",
      "next_state": [
        "free t1",
        "free t2",
        "free t4",
        "grounded t1",
        "grounded t2",
        "grounded t5",
        "holding t3",
        "rel t4 t5"
      ],
      "errors": []
    },
    {
      "step": 3,
      "time": 4.0,
      "action": "(bind t3 t4)",
      "state": [
        "free t1",
        "free t2",
        "free t4",
        "grounded t1",
        "grounded t2",
        "grounded t5",
        "holding t3",
        "rel t4 t5"
      ],
      "effects": {
        "del": [
          "holding t3",
          "free t4"
        ],
        "add": [
          "rel t3 t4",
          "free t3",
          "idle"
        ]
      },
      "status": "valid",
      "next_state": [
        "free t1",
        "free t2",
        "free t3",
        "grounded t1",
        "grounded t2",
        "grounded t5",
        "idle",
        "rel t3 t4",
        "rel t4 t5"
      ],
      "errors": []
    },
    {
      "step": 4,
      "time": 5.0,
      "action": "(lift t2)",
      "state": [
        "free t1",
        "free t2",
        "free t3",
        "grounded t1",
        "grounded t2",
        "grounded t5",
        "idle",
        "rel t3 t4",
        "rel t4 t5"
      ],
      "effects": {
        "del": [
          "grounded t2",
          "free t2",
          "idle"
        ],
        "add": [
          "holding t2"
        ]
      },
      "status": "valid",
      "next_state": [
        "free t1",
        "free t3",
        "grounded t1",
        "grounded t5",
        "holding t2",
        "rel t3 t4",
        "rel t4 t5"
      ],
      "errors": []
    },
    {
      "step": 5,
      "time": 6.0,
      "action": "(bind t2 t3)",
      "state": [
        "free t1",
        "free t3",
        "grounded t1",
        "grounded t5",
        "holding t2",
        "rel t3 t4",
        "rel t4 t5"
      ],
      "effects": {
        "del": [
          "holding t2",
          "free t3"
        ],
        "add": [
          "rel t2 t3",
          "free t2",
          "idle"
        ]
      },
      "status": "valid",
      "next_state": [
        "free t1",
        "free t2",
        "grounded t1",
        "grounded t5",
        "idle",
        "rel t2 t3",
        "rel t3 t4",
        "rel t4 t5"
      ],
      "errors": []
    },
    {
      "step": 6,
      "time": 7.0,
      "action": "(lift t1)",
      "state": [
        "free t1",
        "free t2",
        "grounded t1",
        "grounded t5",
        "idle",
        "rel t2 t3",
        "rel t3 t4",
        "rel t4 t5"
      ],
      "effects": {
        "del": [
          "grounded t1",
          "free t1",
          "idle"
        ],
        "add": [
          "holding t1"
        ]
      },
      "status": "valid",
      "next_state": [
        "free t2",
        "grounded t5",
        "holding t1",
        "rel t2 t3",
        "rel t3 t4",
        "rel t4 t5"
      ],
      "errors": []
    },
    {
      "step": 7,
      "time": 8.0,
      "action": "(bind t1 t2)",
      "state": [
        "free t2",
        "grounded t5",
        "holding t1",
        "rel t2 t3",
        "rel t3 t4",
        "rel t4 t5"
      ],
      "effects": {
        "del": [
          "holding t1",
          "free t2"
        ],
        "add": [
          "rel t1 t2",
          "free t1",
          "idle"
        ]
      },
      "status": "valid",
      "next_state": [
        "free t1",
        "grounded t5",
        "idle",
        "rel t1 t2",
        "rel t2 t3",
        "rel t3 t4",
        "rel t4 t5"
      ],
      "errors": []
    }
  ],
  "errors": [],
  "failed_at_step": null,
  "plan_type": "valid"
}