{
  "domain": "data/planbench_public/mystery_bw/domain.pddl",
  "problem": "data/planbench_public/mystery_bw/problems/mystery_0036.pddl",
  "plan": "data/planbench_public/mystery_bw/plans_corrupt/mystery_0036_corrupt.txt",
  "initial_state": [
    "free t1",
    "free t2",
    "free t3",
    "free t4",
    "free t5",
    "grounded t1",
    "grounded t2",
    "grounded t3",
    "grounded t4",
    "grounded t5",
    "idle"
  ],
  "status": "invalid",
  "exit_code": 1,
  "validator_output": "Checking plan: data/planbench_public/mystery_bw/plans_corrupt/mystery_0036_corrupt.txt\nPlan to validate:\n\nPlan size: 9\n1:\n(lift t4)\n \n2:\n(bind t4 t5)\n \n3:\n(lift t3)\n \n4:\n(bind t3 t4)\n \n5:\n(bind t1 t2)\n \n6:\n(lift t2)\n \n7:\n(bind t2 t3)\n \n8:\n(lift t1)\n \n9:\n(bind t1 t2)\n \n\nPlan Validation details\n-----------------------\n\nChecking next happening (time 1)\nDeleting (grounded t4)\nDeleting (free t4)\nDeleting (idle)\nAdding (holding t4)\n\nChecking next happening (time 2)\nDeleting (holding t4)\nDeleting (free t5)\nAdding (rel t4 t5)\nAdding (free t4)\nAdding (idle)\n\nChecking next happening (time 3)\nDeleting (grounded t3)\nDeleting (free t3)\nDeleting (idle)\nAdding (holding t3)\n\nChecking next happening (time 4)\nDeleting (holding t3)\nDeleting (free t4)\nAdding (rel t3 t4)\nAdding (free t3)\nAdding (idle)\n\nChecking next happening (time 5)\nPlan failed because of unsatisfied precondition in:\n(bind t1 t2)\n\nPlan failed to execute\n\nPlan Repair Advice:\n\n(bind t1 t2) has an unsatisfied precondition at time 5\n(Set (holding t1) to true)\n\n\nFailed plans:\n data/planbench_public/mystery_bw/plans_corrupt/mystery_0036_corrupt.txt \n",
  "transitions": [
    {
      "step": 0,
      "time": 1.0,
      "action": "(lift t4)",
      "state": [
        "free t1",
        "free t2",
        "free t3",
        "free t4",
        "free t5",
        "grounded t1",
        "grounded t2",
        "grounded t3",
        "grounded t4",
        "grounded t5",
        "idle"
      ],
      "effects": {
        "del": [
          "grounded t4",
          "free t4",
          "idle"
        ],
        "add": [
          "holding t4"
        ]
      },
      "status": "valid",
      "next_state": [
        "free t1",
        "free t2",
        "free t3",
        "free t5",
        "grounded t1",
        "grounded t2",
        "grounded t3",
        "grounded t5",
        "holding t4"
      ],
      "errors": []
    },
    {
      "step": 1,
      "time": 2.0,
      "action": "(bind t4 t5)",
      "state": [
        "free t1",
        "free t2",
        "free t3",
        "free t5",
        "grounded t1",
        "grounded t2",
        "grounded t3",
        "grounded t5",
        "holding t4"
      ],
      "effects": {
        "del": [
          "holding t4",
          "free t5"
        ],
        "add": [
          "rel t4 t5",
          "free t4",
          "idle"
        ]
      },
      "status": "valid",
      "next_state": [
        "free t1",
        "free t2",
        "free t3",
        "free t4",
        "grounded t1",
        "grounded t2",
        "grounded t3",
        "grounded t5",
        "idle",
        "rel t4 t5"
      ],
      "errors": []
    },
    {
      "step": 2,
      "time": 3.0,
      "action": "(lift t3)",
      "state": [
        "free t1",
        "free t2",
        "free t3",
        "free t4",
        "grounded t1",
        "grounded t2",
        "grounded t3",
        "grounded t5",
        "idle",
        "rel t4 t5"
      ],
      "effects": {
        "del": [
          "grounded t3",
          "free t3",
          "idle"
        ],
        "add": [
          "holding t3"
        ]
      },
      "status": "valid",
      "next_state": [
        "free t1",
        "free t2",
        "free t4",
        "grounded t1",
        "grounded t2",
        "grounded t5",
        "holding t3",
        "rel t4 t5"
      ],
      "errors": []
    },
    {
      "step": 3,
      "time": 4.0,
      "action": "(bind t3 t4)",
      "state": [
        "free t1",
        "free t2",
        "free t4",
        "grounded t1",
        "grounded t2",
        "grounded t5",
        "holding t3",
        "rel t4 t5"
      ],
      "effects": {
        "del": [
          "holding t3",
          "free t4"
        ],
        "add": [
          "rel t3 t4",
          "free t3",
          "idle"
        ]
      },
      "status": "valid",
      "next_state": [
        "free t1",
        "free t2",
        "free t3",
        "grounded t1",
        "grounded t2",
        "grounded t5",
        "idle",
        "rel t3 t4",
        "rel t4 t5"
      ],
      "errors": []
    },
    {
      "step": 4,
      "time": 5.0,
      "action": "(bind t1 t2)",
      "state": [
        "free t1",
        "free t2",
        "free t3",
        "grounded t1",
        "grounded t2",
        "grounded t5",
        "idle",
        "rel t3 t4",
        "rel t4 t5"
      ],
      "effects": {
        "del": [],
        "add": []
      },
      "status": "invalid",
      "next_state": [
        "free t1",
        "free t2",
        "free t3",
        "grounded t1",
        "grounded t2",
        "grounded t5",
        "idle",
        "rel t3 t4",
        "rel t4 t5"
      ],
      "errors": [
        "unsatisfied precondition in:",
        "(bind t1 t2)"
      ]
    }
  ],
  "errors": [
    "unsatisfied precondition in:",
    "(bind t1 t2)"
  ],
  "failed_at_step": 4,
  "plan_type": "corrupt"
}