{
  "domain": "data/planbench_public/blocksworld/domain.pddl",
  "problem": "data/planbench_public/blocksworld/problems/bw_0060.pddl",
  "plan": "data/planbench_public/blocksworld/plans_valid/bw_0060.txt",
  "initial_state": [
    "clear b1",
    "clear b2",
    "clear b3",
    "clear b4",
    "handempty",
    "on-table b1",
    "on-table b2",
    "on-table b3",
    "on-table b4"
  ],
  "status": "valid",
  "exit_code": 0,
  "validator_output": "Checking plan: data/planbench_public/blocksworld/plans_valid/bw_0060.txt\nPlan to validate:\n\nPlan size: 6\n1:\n(pick-up b3)\n \n2:\n(stack b3 b4)\n \n3:\n(pick-up b2)\n \n4:\n(stack b2 b3)\n \n5:\n(pick-up b1)\n \n6:\n(stack b1 b2)\n \n\nPlan Validation details\n-----------------------\n\nChecking next happening (time 1)\nDeleting (on-table b3)\nDeleting (clear b3)\nDeleting (handempty)\nAdding (holding b3)\n\nChecking next happening (time 2)\nDeleting (holding b3)\nDeleting (clear b4)\nAdding (on b3 b4)\nAdding (clear b3)\nAdding (handempty)\n\nChecking next happening (time 3)\nDeleting (on-table b2)\nDeleting (clear b2)\nDeleting (handempty)\nAdding (holding b2)\n\nChecking next happening (time 4)\nDeleting (holding b2)\nDeleting (clear b3)\nAdding (on b2 b3)\nAdding (clear b2)\nAdding (handempty)\n\nChecking next happening (time 5)\nDeleting (on-table b1)\nDeleting (clear b1)\nDeleting (handempty)\nAdding (holding b1)\n\nChecking next happening (time 6)\nDeleting (holding b1)\nDeleting (clear b2)\nAdding (on b1 b2)\nAdding (clear b1)\nAdding (handempty)\nPlan executed successfully - checking goal\nPlan valid\nFinal value: 6 \n\nSuccessful plans:\nValue: 6\n data/planbench_public/blocksworld/plans_valid/bw_0060.txt 6 \n\n",
  "transitions": [
    {
      "step": 0,
      "time": 1.0,
      "action": "(pick-up b3)",
      "state": [
        "clear b1",
        "clear b2",
        "clear b3",
        "clear b4",
        "handempty",
        "on-table b1",
        "on-table b2",
        "on-table b3",
        "on-table b4"
      ],
      "effects": {
        "del": [
          "on-table b3",
          "clear b3",
          "handempty"
        ],
        "add": [
          "holding b3"
        ]
      },
      "status": "valid",
      "next_state": [
        "clear b1",
        "clear b2",
        "clear b4",
        "holding b3",
        "on-table b1",
        "on-table b2",
        "on-table b4"
      ],
      "errors": []
    },
    {
      "step": 1,
      "time": 2.0,
      "action": "(stack b3 b4)",
      "state": [
        "clear b1",
        "clear b2",
        "clear b4",
        "holding b3",
        "on-table b1",
        "on-table b2",
        "on-table b4"
      ],
      "effects": {
        "del": [
          "holding b3",
          "clear b4"
        ],
        "add": [
          "on b3 b4",
          "clear b3",
          "handempty"
        ]
      },
      "status": "valid",
      "next_state": [
        "clear b1",
        "clear b2",
        "clear b3",
        "handempty",
        "on b3 b4",
        "on-table b1",
        "on-table b2",
        "on-table b4"
      ],
      "errors": []
    },
    {
      "step": 2,
      "time": 3.0,
      "action": "(pick-up b2)",
      "state": [
        "clear b1",
        "clear b2",
        "clear b3",
        "handempty",
        "on b3 b4",
        "on-table b1",
        "on-table b2",
        "on-table b4"
      ],
      "effects": {
        "del": [
          "on-table b2",
          "clear b2",
          "handempty"
        ],
        "add": [
          "holding b2"
        ]
      },
      "status": "valid",
      "next_state": [
        "clear b1",
        "clear b3",
        "holding b2",
        "on b3 b4",
        "on-table b1",
        "on-table b4"
      ],
      "errors": []
    },
    {
      "step": 3,
      "time": 4.0,
      "action": "(stack b2 b3)",
      "state": [
        "clear b1",
        "clear b3",
        "holding b2",
        "on b3 b4",
        "on-table b1",
        "on-table b4"
      ],
      "effects": {
        "del": [
          "holding b2",
          "clear b3"
        ],
        "add": [
          "on b2 b3",
          "clear b2",
          "handempty"
        ]
      },
      "status": "valid",
      "next_state": [
        "clear b1",
        "clear b2",
        "handempty",
        "on b2 b3",
        "on b3 b4",
        "on-table b1",
        "on-table b4"
      ],
      "errors": []
    },
    {
      "step": 4,
      "time": 5.0,
      "action": "(pick-up b1)",
      "state": [
        "clear b1",
        "clear b2",
        "handempty",
        "on b2 b3",
        "on b3 b4",
        "on-table b1",
        "on-table b4"
      ],
      "effects": {
        "del": [
          "on-table b1",
          "clear b1",
          "handempty"
        ],
        "add": [
          "holding b1"
        ]
      },
      "status": "valid",
      "next_state": [
        "clear b2",
        "holding b1",
        "on b2 b3",
        "on b3 b4",
        "on-table b4"
      ],
      "errors": []
    },
    {
      "step": 5,
      "time": 6.0,
      "action": "(stack b1 b2)",
      "state": [
        "clear b2",
        "holding b1",
        "on b2 b3",
        "on b3 b4",
        "on-table b4"
      ],
      "effects": {
        "del": [
          "holding b1",
          "clear b2"
        ],
        "add": [
          "on b1 b2",
          "clear b1",
          "handempty"
        ]
      },
      "status": "valid",
      "next_state": [
        "clear b1",
        "handempty",
        "on b1 b2",
        "on b2 b3",
        "on b3 b4",
        "on-table b4"
      ],
      "errors": []
    }
  ],
  "errors": [],
  "failed_at_step": null,
  "plan_type": "valid"
}