{
  "domain": "data/planbench_public/blocksworld/domain.pddl",
  "problem": "data/planbench_public/blocksworld/problems/bw_0026.pddl",
  "plan": "data/planbench_public/blocksworld/plans_corrupt/bw_0026_corrupt.txt",
  "initial_state": [
    "clear b1",
    "clear b2",
    "clear b3",
    "clear b4",
    "clear b5",
    "handempty",
    "on-table b1",
    "on-table b2",
    "on-table b3",
    "on-table b4",
    "on-table b5"
  ],
  "status": "invalid",
  "exit_code": 1,
  "validator_output": "Checking plan: data/planbench_public/blocksworld/plans_corrupt/bw_0026_corrupt.txt\nPlan to validate:\n\nPlan size: 9\n1:\n(pick-up b4)\n \n2:\n(stack b4 b5)\n \n3:\n(pick-up b3)\n \n4:\n(stack b1 b2)\n \n5:\n(stack b3 b4)\n \n6:\n(pick-up b2)\n \n7:\n(stack b2 b3)\n \n8:\n(pick-up b1)\n \n9:\n(stack b1 b2)\n \n\nPlan Validation details\n-----------------------\n\nChecking next happening (time 1)\nDeleting (on-table b4)\nDeleting (clear b4)\nDeleting (handempty)\nAdding (holding b4)\n\nChecking next happening (time 2)\nDeleting (holding b4)\nDeleting (clear b5)\nAdding (on b4 b5)\nAdding (clear b4)\nAdding (handempty)\n\nChecking next happening (time 3)\nDeleting (on-table b3)\nDeleting (clear b3)\nDeleting (handempty)\nAdding (holding b3)\n\nChecking next happening (time 4)\nPlan failed because of unsatisfied precondition in:\n(stack b1 b2)\n\nPlan failed to execute\n\nPlan Repair Advice:\n\n(stack b1 b2) has an unsatisfied precondition at time 4\n(Set (holding b1) to true)\n\n\nFailed plans:\n data/planbench_public/blocksworld/plans_corrupt/bw_0026_corrupt.txt \n",
  "transitions": [
    {
      "step": 0,
      "time": 1.0,
      "action": "(pick-up b4)",
      "state": [
        "clear b1",
        "clear b2",
        "clear b3",
        "clear b4",
        "clear b5",
        "handempty",
        "on-table b1",
        "on-table b2",
        "on-table b3",
        "on-table b4",
        "on-table b5"
      ],
      "effects": {
        "del": [
          "on-table b4",
          "clear b4",
          "handempty"
        ],
        "add": [
          "holding b4"
        ]
      },
      "status": "valid",
      "next_state": [
        "clear b1",
        "clear b2",
        "clear b3",
        "clear b5",
        "holding b4",
        "on-table b1",
        "on-table b2",
        "on-table b3",
        "on-table b5"
      ],
      "errors": []
    },
    {
      "step": 1,
      "time": 2.0,
      "action": "(stack b4 b5)",
      "state": [
        "clear b1",
        "clear b2",
        "clear b3",
        "clear b5",
        "holding b4",
        "on-table b1",
        "on-table b2",
        "on-table b3",
        "on-table b5"
      ],
      "effects": {
        "del": [
          "holding b4",
          "clear b5"
        ],
        "add": [
          "on b4 b5",
          "clear b4",
          "handempty"
        ]
      },
      "status": "valid",
      "next_state": [
        "clear b1",
        "clear b2",
        "clear b3",
        "clear b4",
        "handempty",
        "on b4 b5",
        "on-table b1",
        "on-table b2",
        "on-table b3",
        "on-table b5"
      ],
      "errors": []
    },
    {
      "step": 2,
      "time": 3.0,
      "action": "(pick-up b3)",
      "state": [
        "clear b1",
        "clear b2",
        "clear b3",
        "clear b4",
        "handempty",
        "on b4 b5",
        "on-table b1",
        "on-table b2",
        "on-table b3",
        "on-table b5"
      ],
      "effects": {
        "del": [
          "on-table b3",
          "clear b3",
          "handempty"
        ],
        "add": [
          "holding b3"
        ]
      },
      "status": "valid",
      "next_state": [
        "clear b1",
        "clear b2",
        "clear b4",
        "holding b3",
        "on b4 b5",
        "on-table b1",
        "on-table b2",
        "on-table b5"
      ],
      "errors": []
    },
    {
      "step": 3,
      "time": 4.0,
      "action": "(stack b1 b2)",
      "state": [
        "clear b1",
        "clear b2",
        "clear b4",
        "holding b3",
        "on b4 b5",
        "on-table b1",
        "on-table b2",
        "on-table b5"
      ],
      "effects": {
        "del": [],
        "add": []
      },
      "status": "invalid",
      "next_state": [
        "clear b1",
        "clear b2",
        "clear b4",
        "holding b3",
        "on b4 b5",
        "on-table b1",
        "on-table b2",
        "on-table b5"
      ],
      "errors": [
        "unsatisfied precondition in:",
        "(stack b1 b2)"
      ]
    }
  ],
  "errors": [
    "unsatisfied precondition in:",
    "(stack b1 b2)"
  ],
  "failed_at_step": 3,
  "plan_type": "corrupt"
}